{
    "args": {
        "dafny_file": "/benchmarks/09-CounterNoStateMachine.dfy",
        "procedure_name": "Impl$$_module.__default.Incrementer",
        "option_selector_name": "stdin",
        "results_filename": "/result/09-counternostatemachine-dfy-impl-module-default-incrementer-stdin-1-none-0-928796253.json",
        "seed": "0",
        "num_instances": 1,
        "dafny_command": "/opt/dafny/dafny",
        "commit_hash": "",
        "timeout": 600,
        "cpu_queue": "bw-uni-cluster-single"
    },
    "commit_hash": "",
    "total_runtime": {
        "start": 1656377799.6318033,
        "start_readable": "2022-06-28T02:56:39.631803",
        "end": 1656377837.7555401,
        "end_readable": "2022-06-28T02:57:17.755540",
        "duration": "38.1237368584"
    },
    "termination_reason": "instance termination",
    "instances": [
        {
            "id": 0,
            "cpu": 0,
            "cmd": [
                "/opt/dafny/dafny",
                "/benchmarks/09-CounterNoStateMachine.dfy",
                "/proc:Impl$$_module.__default.Incrementer",
                "/compile:0",
                "/rlimit:9999999",
                "/xml:/tmp/tmpmrbuim6u.xml",
                "/proverOpt:O:smt.mbqi=true"
            ],
            "diversification": [
                "/proverOpt:O:smt.mbqi=true"
            ],
            "stdout": [],
            "stderr": [],
            "xml": "no element found: line 1, column 0"
        },
        {
            "id": 1,
            "cpu": 10,
            "cmd": [
                "/opt/dafny/dafny",
                "/benchmarks/09-CounterNoStateMachine.dfy",
                "/proc:Impl$$_module.__default.Incrementer",
                "/compile:0",
                "/rlimit:9999999",
                "/xml:/tmp/tmpggvlni6k.xml",
                "/proverOpt:O:rewriter.cache_all=true"
            ],
            "diversification": [
                "/proverOpt:O:rewriter.cache_all=true"
            ],
            "stdout": [],
            "stderr": [],
            "xml": "no element found: line 1, column 0"
        },
        {
            "id": 2,
            "cpu": 20,
            "cmd": [
                "/opt/dafny/dafny",
                "/benchmarks/09-CounterNoStateMachine.dfy",
                "/proc:Impl$$_module.__default.Incrementer",
                "/compile:0",
                "/rlimit:9999999",
                "/xml:/tmp/tmpt5u77k0e.xml",
                "/vcsMaxKeepGoingSplits:32",
                "/vcsKeepGoingTimeout:50"
            ],
            "diversification": [
                "/vcsMaxKeepGoingSplits:32",
                "/vcsKeepGoingTimeout:50"
            ],
            "stdout": [
                "b''",
                "b'Dafny program verifier finished with 1 verified, 0 errors'"
            ],
            "stderr": [],
            "xml": {
                "version": "3.4.2.40221",
                "command": "/opt/dafny/Dafny.dll /benchmarks/09-CounterNoStateMachine.dfy /proc:Impl$$_module.__default.Incrementer /compile:0 /rlimit:9999999 /xml:/tmp/tmpt5u77k0e.xml /vcsMaxKeepGoingSplits:32 /vcsKeepGoingTimeout:50",
                "methods": [
                    {
                        "name": "Impl$$_module.__default.Incrementer",
                        "startTime": "2022-06-28 00:56:42+00:00",
                        "finished": true,
                        "endTime": "2022-06-28 00:57:17+00:00",
                        "duration": 35.5270071,
                        "outcome": "correct"
                    }
                ]
            }
        }
    ]
}