{
    "args": {
        "dafny_file": "/benchmarks/TreeBarrier.dfy",
        "procedure_name": "Impl$$_module.Node.barrier",
        "option_selector_name": "stdin",
        "results_filename": "/result/treebarrier-dfy-impl-module-node-barrier-stdin-1-none-0-4080775249.json",
        "seed": "0",
        "num_instances": 1,
        "dafny_command": "/opt/dafny/dafny",
        "commit_hash": "",
        "timeout": 600,
        "cpu_queue": "bw-uni-cluster-single"
    },
    "commit_hash": "",
    "total_runtime": {
        "start": 1658017890.3798733,
        "start_readable": "2022-07-17T02:31:30.379873",
        "end": 1658017897.5369787,
        "end_readable": "2022-07-17T02:31:37.536979",
        "duration": "7.1571054459"
    },
    "termination_reason": "instance termination",
    "instances": [
        {
            "id": 0,
            "cpu": 0,
            "cmd": [
                "/opt/dafny/dafny",
                "/benchmarks/TreeBarrier.dfy",
                "/proc:Impl$$_module.Node.barrier",
                "/compile:0",
                "/rlimit:9999999",
                "/xml:/tmp/tmpzfsbvxdu.xml",
                "/proverOpt:O:smt.mbqi=false"
            ],
            "diversification": [
                "/proverOpt:O:smt.mbqi=false"
            ],
            "stdout": [],
            "stderr": [],
            "xml": "no element found: line 1, column 0"
        },
        {
            "id": 1,
            "cpu": 10,
            "cmd": [
                "/opt/dafny/dafny",
                "/benchmarks/TreeBarrier.dfy",
                "/proc:Impl$$_module.Node.barrier",
                "/compile:0",
                "/rlimit:9999999",
                "/xml:/tmp/tmpkh527pal.xml",
                "/proverOpt:O:model_evaluator.array_as_stores=false"
            ],
            "diversification": [
                "/proverOpt:O:model_evaluator.array_as_stores=false"
            ],
            "stdout": [
                "b''",
                "b'Dafny program verifier finished with 1 verified, 0 errors'"
            ],
            "stderr": [],
            "xml": {
                "version": "3.4.2.40221",
                "command": "/opt/dafny/Dafny.dll /benchmarks/TreeBarrier.dfy /proc:Impl$$_module.Node.barrier /compile:0 /rlimit:9999999 /xml:/tmp/tmpkh527pal.xml /proverOpt:O:model_evaluator.array_as_stores=false",
                "methods": [
                    {
                        "name": "Impl$$_module.Node.barrier",
                        "startTime": "2022-07-17 00:31:32+00:00",
                        "finished": true,
                        "endTime": "2022-07-17 00:31:37+00:00",
                        "duration": 5.4011374,
                        "outcome": "correct"
                    }
                ]
            }
        }
    ]
}