{
    "args": {
        "dafny_file": "/benchmarks/11-MutexGuard2.dfy",
        "procedure_name": "SetData",
        "option_selector_name": "split-limit-diversification",
        "results_filename": "/result/11-mutexguard2-dfy-setdata-split-limit-diversification-10-0-522591.json",
        "seed": "522591",
        "num_instances": 10,
        "dafny_command": "/opt/dafny/dafny",
        "only_instances": [
            0
        ],
        "commit_hash": ""
    },
    "commit_hash": "",
    "total_runtime": {
        "start": 1647726444.883122,
        "start_readable": "2022-03-19T22:47:24.883122",
        "end": 1647726502.8887646,
        "end_readable": "2022-03-19T22:48:22.888765",
        "duration": "58.0056426525"
    },
    "instances": [
        {
            "id": 0,
            "cmd": [
                "/opt/dafny/dafny",
                "/benchmarks/11-MutexGuard2.dfy",
                "/proc:*SetData",
                "/xml:/tmp/tmph0eb61qm.xml",
                "/vcsMaxKeepGoingSplits:2"
            ],
            "diversification": [
                "/vcsMaxKeepGoingSplits:2"
            ],
            "stdout": [
                "b''",
                "b'Dafny program verifier finished with 2 verified, 0 errors'"
            ],
            "stderr": [],
            "xml": {
                "version": "3.4.2.40221",
                "command": "/opt/dafny/Dafny.dll /benchmarks/11-MutexGuard2.dfy /proc:*SetData /xml:/tmp/tmph0eb61qm.xml /vcsMaxKeepGoingSplits:2",
                "methods": [
                    {
                        "name": "CheckWellformed$$_module.__default.SetData",
                        "startTime": "2022-03-19 21:47:27+00:00",
                        "finished": true,
                        "endTime": "2022-03-19 21:47:27+00:00",
                        "duration": 0.3084354,
                        "outcome": "correct"
                    },
                    {
                        "name": "Impl$$_module.__default.SetData",
                        "startTime": "2022-03-19 21:47:27+00:00",
                        "finished": true,
                        "endTime": "2022-03-19 21:48:22+00:00",
                        "duration": 55.2187825,
                        "outcome": "correct"
                    }
                ]
            }
        }
    ]
}