{
    "args": {
        "dafny_file": "/benchmarks/InductivePredicates.dfy",
        "procedure_name": "Impl$$Alt.__default.MyLemma__NotSoNice_h",
        "option_selector_name": "stdin",
        "results_filename": "/result/inductivepredicates-dfy-impl-alt-default-mylemma-notsonice-h-stdin-1-none-3-2021486602.json",
        "seed": "3",
        "num_instances": 1,
        "dafny_command": "/opt/dafny/dafny",
        "commit_hash": "",
        "timeout": 600,
        "cpu_queue": "bw-uni-cluster-single"
    },
    "commit_hash": "",
    "total_runtime": {
        "start": 1659964752.3248398,
        "start_readable": "2022-08-08T15:19:12.324840",
        "end": 1659964777.1777942,
        "end_readable": "2022-08-08T15:19:37.177794",
        "duration": "24.8529543877"
    },
    "termination_reason": "instance termination",
    "instances": [
        {
            "id": 0,
            "cpu": 0,
            "cmd": [
                "/opt/dafny/dafny",
                "/benchmarks/InductivePredicates.dfy",
                "/proc:Impl$$Alt.__default.MyLemma__NotSoNice_h",
                "/compile:0",
                "/rlimit:9999999",
                "/xml:/tmp/tmpiovjvjyz.xml",
                "/proverOpt:O:opt.maxres.add_upper_bound_block=true"
            ],
            "diversification": [
                "/proverOpt:O:opt.maxres.add_upper_bound_block=true"
            ],
            "stdout": [
                "b''",
                "b'Dafny program verifier finished with 1 verified, 0 errors'"
            ],
            "stderr": [],
            "xml": {
                "version": "3.4.2.40221",
                "command": "/opt/dafny/Dafny.dll /benchmarks/InductivePredicates.dfy /proc:Impl$$Alt.__default.MyLemma__NotSoNice_h /compile:0 /rlimit:9999999 /xml:/tmp/tmpiovjvjyz.xml /proverOpt:O:opt.maxres.add_upper_bound_block=true",
                "methods": [
                    {
                        "name": "Impl$$Alt.__default.MyLemma__NotSoNice_h",
                        "startTime": "2022-08-08 13:19:14+00:00",
                        "finished": true,
                        "endTime": "2022-08-08 13:19:36+00:00",
                        "duration": 22.7605453,
                        "outcome": "correct"
                    }
                ]
            }
        }
    ]
}