{
    "args": {
        "dafny_file": "/benchmarks/TreeBarrier.dfy",
        "procedure_name": "Impl$$_module.Node.barrier",
        "option_selector_name": "stdin",
        "results_filename": "/result/treebarrier-dfy-impl-module-node-barrier-stdin-1-none-2-2292656499.json",
        "seed": "2",
        "num_instances": 1,
        "dafny_command": "/opt/dafny/dafny",
        "commit_hash": "",
        "timeout": 600,
        "cpu_queue": "bw-uni-cluster-single",
        "pairs": [
            [
                "call_number",
                "36306"
            ],
            [
                "job_number",
                "6"
            ],
            [
                "call_in_job_number",
                "195"
            ]
        ]
    },
    "key-values": {
        "call_number": "36306",
        "job_number": "6",
        "call_in_job_number": "195"
    },
    "commit_hash": "",
    "total_runtime": {
        "start": 1661228754.359345,
        "start_readable": "2022-08-23T06:25:54.359345",
        "end": 1661228761.4398708,
        "end_readable": "2022-08-23T06:26:01.439871",
        "duration": "7.0805258751"
    },
    "termination_reason": "instance termination",
    "instances": [
        {
            "id": 0,
            "cpu": 0,
            "cmd": [
                "/opt/dafny/dafny",
                "/benchmarks/TreeBarrier.dfy",
                "/proc:Impl$$_module.Node.barrier",
                "/compile:0",
                "/rlimit:9999999",
                "/xml:/tmp/tmp_qa0g9qv.xml",
                "/vcsMaxKeepGoingSplits:32",
                "/vcsKeepGoingTimeout:30"
            ],
            "diversification": [
                "/vcsMaxKeepGoingSplits:32",
                "/vcsKeepGoingTimeout:30"
            ],
            "stdout": [
                "b''",
                "b'Dafny program verifier finished with 1 verified, 0 errors'"
            ],
            "stderr": [],
            "xml": {
                "version": "3.4.2.40221",
                "command": "/opt/dafny/Dafny.dll /benchmarks/TreeBarrier.dfy /proc:Impl$$_module.Node.barrier /compile:0 /rlimit:9999999 /xml:/tmp/tmp_qa0g9qv.xml /vcsMaxKeepGoingSplits:32 /vcsKeepGoingTimeout:30",
                "methods": [
                    {
                        "name": "Impl$$_module.Node.barrier",
                        "startTime": "2022-08-23 04:25:55+00:00",
                        "finished": true,
                        "endTime": "2022-08-23 04:26:01+00:00",
                        "duration": 5.3801019,
                        "outcome": "correct"
                    }
                ]
            }
        }
    ]
}