{
    "args": {
        "dafny_file": "/benchmarks/12-MutexLifetime-short.dfy",
        "procedure_name": "Impl$$_module.MutexGuardU32.__ctor",
        "option_selector_name": "stdin",
        "results_filename": "/result/12-mutexlifetime-short-dfy-impl-module-mutexguardu32-ctor-stdin-1-none-3-1048109085.json",
        "seed": "3",
        "num_instances": 1,
        "dafny_command": "/opt/dafny/dafny",
        "commit_hash": "",
        "timeout": 600
    },
    "commit_hash": "",
    "total_runtime": {
        "start": 1654993086.3033016,
        "start_readable": "2022-06-12T02:18:06.303302",
        "end": 1654993151.403439,
        "end_readable": "2022-06-12T02:19:11.403439",
        "duration": "65.1001374722"
    },
    "termination_reason": "instance termination",
    "instances": [
        {
            "id": 0,
            "cpu": 0,
            "cmd": [
                "/opt/dafny/dafny",
                "/benchmarks/12-MutexLifetime-short.dfy",
                "/proc:Impl$$_module.MutexGuardU32.__ctor",
                "/xml:/tmp/tmp9i202nv_.xml",
                "/vcsMaxKeepGoingSplits:2",
                "/vcsKeepGoingTimeout:50",
                "/vcsCores:7"
            ],
            "diversification": [
                "/vcsMaxKeepGoingSplits:2",
                "/vcsKeepGoingTimeout:50",
                "/vcsCores:7"
            ],
            "stdout": [
                "b''",
                "b'Dafny program verifier finished with 1 verified, 0 errors'"
            ],
            "stderr": [],
            "xml": {
                "version": "3.4.2.40221",
                "command": "/opt/dafny/Dafny.dll /benchmarks/12-MutexLifetime-short.dfy /proc:Impl$$_module.MutexGuardU32.__ctor /xml:/tmp/tmp9i202nv_.xml /vcsMaxKeepGoingSplits:2 /vcsKeepGoingTimeout:50 /vcsCores:7",
                "methods": [
                    {
                        "name": "Impl$$_module.MutexGuardU32.__ctor",
                        "startTime": "2022-06-12 00:18:09+00:00",
                        "finished": true,
                        "endTime": "2022-06-12 00:19:11+00:00",
                        "duration": 62.1023425,
                        "outcome": "correct"
                    }
                ]
            }
        }
    ]
}