{
    "args": {
        "dafny_file": "/benchmarks/UnionFind.dfy",
        "procedure_name": "Impl$$M3.UnionFind.Join",
        "option_selector_name": "stdin",
        "results_filename": "/result/unionfind-dfy-impl-m3-unionfind-join-stdin-1-none-3-1760450611.json",
        "seed": "3",
        "num_instances": 1,
        "dafny_command": "/opt/dafny/dafny",
        "commit_hash": "",
        "timeout": 600,
        "cpu_queue": "no-assignment"
    },
    "commit_hash": "",
    "total_runtime": {
        "start": 1656758297.5504396,
        "start_readable": "2022-07-02T12:38:17.550440",
        "end": 1656758309.1415281,
        "end_readable": "2022-07-02T12:38:29.141528",
        "duration": "11.5910885334"
    },
    "termination_reason": "instance termination",
    "instances": [
        {
            "id": 0,
            "cpu": null,
            "cmd": [
                "/opt/dafny/dafny",
                "/benchmarks/UnionFind.dfy",
                "/proc:Impl$$M3.UnionFind.Join",
                "/compile:0",
                "/rlimit:9999999",
                "/xml:/tmp/tmpjlbbnmze.xml",
                "/vcsMaxSplits:6",
                "/vcsCores:48"
            ],
            "diversification": [
                "/vcsMaxSplits:6",
                "/vcsCores:48"
            ],
            "stdout": [
                "b''",
                "b'Dafny program verifier finished with 1 verified, 0 errors'"
            ],
            "stderr": [],
            "xml": {
                "version": "3.4.2.40221",
                "command": "/opt/dafny/Dafny.dll /benchmarks/UnionFind.dfy /proc:Impl$$M3.UnionFind.Join /compile:0 /rlimit:9999999 /xml:/tmp/tmpjlbbnmze.xml /vcsMaxSplits:6 /vcsCores:48",
                "methods": [
                    {
                        "name": "Impl$$M3.UnionFind.Join",
                        "startTime": "2022-07-02 10:38:20+00:00",
                        "finished": true,
                        "endTime": "2022-07-02 10:38:28+00:00",
                        "duration": 8.6038097,
                        "outcome": "correct"
                    }
                ]
            }
        }
    ]
}