{
    "args": {
        "dafny_file": "/benchmarks/12-MutexLifetime-long.dfy",
        "procedure_name": "Impl$$_module.MutexGuardU32.__ctor",
        "option_selector_name": "stdin",
        "results_filename": "/result/12-mutexlifetime-long-dfy-impl-module-mutexguardu32-ctor-stdin-1-none-752764-1234574800.json",
        "seed": "752764",
        "num_instances": 1,
        "dafny_command": "/opt/dafny/dafny",
        "only_instances": null,
        "commit_hash": ""
    },
    "commit_hash": "",
    "total_runtime": {
        "start": 1652054197.984366,
        "start_readable": "2022-05-09T01:56:37.984366",
        "end": 1652054300.209874,
        "end_readable": "2022-05-09T01:58:20.209874",
        "duration": "102.2255079746"
    },
    "instances": [
        {
            "id": 0,
            "cmd": [
                "/opt/dafny/dafny",
                "/benchmarks/12-MutexLifetime-long.dfy",
                "/proc:Impl$$_module.MutexGuardU32.__ctor",
                "/xml:/tmp/tmpx0rn4w2b.xml",
                "/proverOpt:O:smt.qi.eager_threshold=10"
            ],
            "diversification": [
                "/proverOpt:O:smt.qi.eager_threshold=10"
            ],
            "stdout": [
                "b''",
                "b'Dafny program verifier finished with 1 verified, 0 errors'"
            ],
            "stderr": [],
            "xml": {
                "version": "3.4.2.40221",
                "command": "/opt/dafny/Dafny.dll /benchmarks/12-MutexLifetime-long.dfy /proc:Impl$$_module.MutexGuardU32.__ctor /xml:/tmp/tmpx0rn4w2b.xml /proverOpt:O:smt.qi.eager_threshold=10",
                "methods": [
                    {
                        "name": "Impl$$_module.MutexGuardU32.__ctor",
                        "startTime": "2022-05-08 23:56:41+00:00",
                        "finished": true,
                        "endTime": "2022-05-08 23:58:20+00:00",
                        "duration": 99.0313018,
                        "outcome": "correct"
                    }
                ]
            }
        }
    ]
}